llm_wrapper/__init__.py
llm_wrapper/client.py
llm_wrapper/models.py
llm_wrapper/providers/__init__.py
llm_wrapper/providers/anthropic.py
llm_wrapper/providers/base.py
llm_wrapper/providers/gemini.py
llm_wrapper/providers/openai.py
awesome_llm_wrapper-0.1.2.dist-info/METADATA
awesome_llm_wrapper-0.1.2.dist-info/WHEEL
awesome_llm_wrapper-0.1.2.dist-info/top_level.txt
awesome_llm_wrapper-0.1.2.dist-info/RECORD
