Metadata-Version: 2.4
Name: awesome-llm-wrapper
Version: 0.1.2
Summary: A unified wrapper for multiple LLM APIs including OpenAI, Gemini, and Anthropic
Author-email: Amirsalar Abedini <abediniamirsalar@gmail.com>
License-Expression: MIT
Keywords: llm,ai,openai,gemini,anthropic,wrapper,api
Classifier: Programming Language :: Python :: 3
Classifier: Operating System :: OS Independent
Classifier: Intended Audience :: Developers
Classifier: Topic :: Software Development :: Libraries :: Python Modules
Requires-Python: >=3.8
Requires-Dist: requests>=2.28.0
Requires-Dist: python-dotenv>=0.20.0
Provides-Extra: dev
Requires-Dist: pytest>=7.0.0; extra == "dev"
Requires-Dist: black>=22.0.0; extra == "dev"
Requires-Dist: isort>=5.10.0; extra == "dev"
